WeiXueyuanLinuxJiaocheng/README.md
WeiXueyuanLinuxJiaocheng/__init__.py
WeiXueyuanLinuxJiaocheng/__main__.py
WeiXueyuanLinuxJiaocheng/file.epub
WeiXueyuanLinuxJiaocheng/index.html
WeiXueyuanLinuxJiaocheng/css/__init__.py
WeiXueyuanLinuxJiaocheng/css/annotations.css
WeiXueyuanLinuxJiaocheng/css/main.css
WeiXueyuanLinuxJiaocheng/css/normalize.css
WeiXueyuanLinuxJiaocheng/css/popup.css
WeiXueyuanLinuxJiaocheng/font/__init__.py
WeiXueyuanLinuxJiaocheng/font/fontello.eot
WeiXueyuanLinuxJiaocheng/font/fontello.svg
WeiXueyuanLinuxJiaocheng/font/fontello.ttf
WeiXueyuanLinuxJiaocheng/font/fontello.woff
WeiXueyuanLinuxJiaocheng/img/__init__.py
WeiXueyuanLinuxJiaocheng/img/annotator-glyph-sprite.png
WeiXueyuanLinuxJiaocheng/img/annotator-icon-sprite.png
WeiXueyuanLinuxJiaocheng/img/apple-touch-icon.png
WeiXueyuanLinuxJiaocheng/img/cancelfullscreen.png
WeiXueyuanLinuxJiaocheng/img/close.png
WeiXueyuanLinuxJiaocheng/img/fullscreen.png
WeiXueyuanLinuxJiaocheng/img/loader.gif
WeiXueyuanLinuxJiaocheng/img/menu-icon.png
WeiXueyuanLinuxJiaocheng/img/save.png
WeiXueyuanLinuxJiaocheng/img/saved.png
WeiXueyuanLinuxJiaocheng/img/settings-s.png
WeiXueyuanLinuxJiaocheng/img/settings.png
WeiXueyuanLinuxJiaocheng/img/star.png
WeiXueyuanLinuxJiaocheng/js/__init__.py
WeiXueyuanLinuxJiaocheng/js/epub.js
WeiXueyuanLinuxJiaocheng/js/epub.min.js
WeiXueyuanLinuxJiaocheng/js/epub.min.map
WeiXueyuanLinuxJiaocheng/js/hooks.min.js
WeiXueyuanLinuxJiaocheng/js/hooks.min.map
WeiXueyuanLinuxJiaocheng/js/reader.js
WeiXueyuanLinuxJiaocheng/js/reader.js.map
WeiXueyuanLinuxJiaocheng/js/reader.min.js
WeiXueyuanLinuxJiaocheng/js/reader.min.map
WeiXueyuanLinuxJiaocheng/js/hooks/__init__.py
WeiXueyuanLinuxJiaocheng/js/hooks/extensions/__init__.py
WeiXueyuanLinuxJiaocheng/js/hooks/extensions/highlight.js
WeiXueyuanLinuxJiaocheng/js/libs/__init__.py
WeiXueyuanLinuxJiaocheng/js/libs/jquery.min.js
WeiXueyuanLinuxJiaocheng/js/libs/localforage.min.js
WeiXueyuanLinuxJiaocheng/js/libs/screenfull.js
wei_xueyuan_linux_jiaocheng-2024.3.6.0.dist-info/METADATA
wei_xueyuan_linux_jiaocheng-2024.3.6.0.dist-info/WHEEL
wei_xueyuan_linux_jiaocheng-2024.3.6.0.dist-info/entry_points.txt
wei_xueyuan_linux_jiaocheng-2024.3.6.0.dist-info/top_level.txt
wei_xueyuan_linux_jiaocheng-2024.3.6.0.dist-info/RECORD
